pynanovna/__init__.py
pynanovna/calibration/calibration.py
pynanovna/hardware/AVNA.py
pynanovna/hardware/Hardware.py
pynanovna/hardware/JNCRadio_VNA_3G.py
pynanovna/hardware/NanoVNA.py
pynanovna/hardware/NanoVNA_F.py
pynanovna/hardware/NanoVNA_F_V2.py
pynanovna/hardware/NanoVNA_H.py
pynanovna/hardware/NanoVNA_H4.py
pynanovna/hardware/NanoVNA_V2.py
pynanovna/hardware/SV4401A.py
pynanovna/hardware/SV6301A.py
pynanovna/hardware/Serial.py
pynanovna/hardware/TinySA.py
pynanovna/hardware/VNABase.py
pynanovna/hardware/Version.py
pynanovna/pynanovna.py
pynanovna/utils.py
pynanovna/vis.py
pynanovna-1.0.2.dist-info/LICENCE
pynanovna-1.0.2.dist-info/METADATA
pynanovna-1.0.2.dist-info/WHEEL
pynanovna-1.0.2.dist-info/RECORD
