Metadata-Version: 2.1
Name: pynanovna
Version: 1.0.2
Summary: A package to use a NanoVNA
Home-page: https://github.com/bergkvistteo/pynanovna
License: GPL-3.0-or-later
Author: Teo Bergkvist
Author-email: bergkvist.teo@protonmail.com
Requires-Python: >=3.9
Classifier: Development Status :: 4 - Beta
Classifier: Intended Audience :: Science/Research
Classifier: License :: OSI Approved :: GNU General Public License v3 or later (GPLv3+)
Classifier: Programming Language :: Python :: 3
Classifier: Programming Language :: Python :: 3.9
Classifier: Programming Language :: Python :: 3.10
Classifier: Programming Language :: Python :: 3.11
Classifier: Programming Language :: Python :: 3.12
Classifier: Programming Language :: Python :: 3.13
Classifier: Topic :: Scientific/Engineering
Requires-Dist: matplotlib (>=3.6.2)
Requires-Dist: numpy (>=1.26.4)
Requires-Dist: pyserial (>=3.5)
Requires-Dist: scipy (>=1.13.0)
Project-URL: Documentation, https://pynanovna.readthedocs.io
Project-URL: Repository, https://github.com/bergkvistteo/pynanovna
